pyjedai/__init__.py
pyjedai/_version.py
pyjedai/block_building.py
pyjedai/block_cleaning.py
pyjedai/clustering.py
pyjedai/comparison_cleaning.py
pyjedai/datamodel.py
pyjedai/evaluation.py
pyjedai/joins.py
pyjedai/llm_matching.py
pyjedai/logs.py
pyjedai/matching.py
pyjedai/prioritization.py
pyjedai/string_matchers.py
pyjedai/utils.py
pyjedai/vector_based_blocking.py
pyjedai/visualization.py
pyjedai/workflow.py
pyjedai/schema/clustering.py
pyjedai/schema/matching.py
pyjedai/schema/schema_model.py
pyjedai/schema/utils.py
pyjedai/spatial/filtering.py
pyjedai/spatial/initialization.py
pyjedai/spatial/verification.py
pyjedai-0.3.6.dist-info/licenses/LICENSE
pyjedai-0.3.6.dist-info/METADATA
pyjedai-0.3.6.dist-info/WHEEL
pyjedai-0.3.6.dist-info/top_level.txt
pyjedai-0.3.6.dist-info/RECORD
