Metadata-Version: 2.4
Name: pyjedai
Version: 0.3.6
Summary: An open-source library that builds powerful end-to-end Entity Resolution workflows.
Author-email: Lefteris Stetsikas <lstetsikas3@gmail.com>, Konstantinos Nikoletos <nikoletos.kon@gmail.com>, George Papadakis <gpapadis84@gmail.com>, Jakub Maciejewski <jacobb.maciejewski@gmail.com>, Manolis Koubarakis <koubarak@di.uoa.gr>
License: Apache Software License 2.0
Project-URL: Homepage, http://pyjedai.rtfd.io
Project-URL: Documentation, http://pyjedai.rtfd.io
Project-URL: Bug Tracker, https://github.com/AI-team-UoA/pyJedAI/issues
Project-URL: Source code, https://github.com/AI-team-UoA/pyJedAI/tree/main/pyjedai
Keywords: deduplication,entity-resolution,link-discovery
Classifier: License :: OSI Approved :: Apache Software License
Classifier: Programming Language :: Python
Classifier: Programming Language :: Python :: 3
Classifier: Programming Language :: Python :: 3.8
Classifier: Programming Language :: Python :: 3.9
Classifier: Programming Language :: Python :: 3.10
Classifier: Programming Language :: Python :: 3.11
Classifier: Programming Language :: Python :: Implementation
Classifier: Intended Audience :: Information Technology
Classifier: Intended Audience :: Science/Research
Classifier: Intended Audience :: Developers
Classifier: Natural Language :: English
Classifier: Operating System :: Microsoft :: Windows
Classifier: Operating System :: Unix
Classifier: Operating System :: iOS
Classifier: Topic :: Database
Classifier: Topic :: Scientific/Engineering :: Artificial Intelligence
Classifier: Topic :: Software Development :: Libraries :: Python Modules
Requires-Python: >=3.9
License-File: LICENSE
Requires-Dist: matplotlib
Requires-Dist: networkx
Requires-Dist: nltk
Requires-Dist: numpy<3.0
Requires-Dist: pandas
Requires-Dist: scipy
Requires-Dist: seaborn
Requires-Dist: tqdm
Requires-Dist: transformers
Requires-Dist: sentence-transformers
Requires-Dist: faiss-cpu
Requires-Dist: valentine; python_version > "3.7"
Requires-Dist: ordered-set
Requires-Dist: shapely
Requires-Dist: ollama
Requires-Dist: py-stringcompare
Requires-Dist: ray
Provides-Extra: dev
Requires-Dist: pip-tools; extra == "dev"
Requires-Dist: pytest; extra == "dev"
Provides-Extra: with-gensim
Requires-Dist: numpy<2.0,>=1.7; extra == "with-gensim"
Requires-Dist: gensim; extra == "with-gensim"
Requires-Dist: scipy==1.12; extra == "with-gensim"
Dynamic: license-file
